{
  "results": [
    {
      "address_components": [
        {
          "long_name": "182",
          "short_name": "182",
          "types": [
            "street_number"
          ]
        },
        {
          "long_name": "Dorchester Drive",
          "short_name": "Dorchester Dr",
          "types": [
            "route"
          ]
        },
        {
          "long_name": "Leisuretowne",
          "short_name": "Leisuretowne",
          "types": [
            "neighborhood",
            "political"
          ]
        },
        {
          "long_name": "Southampton Township",
          "short_name": "Southampton Township",
          "types": [
            "locality",
            "political"
          ]
        },
        {
          "long_name": "Burlington County",
          "short_name": "Burlington County",
          "types": [
            "administrative_area_level_2",
            "political"
          ]
        },
        {
          "long_name": "New Jersey",
          "short_name": "NJ",
          "types": [
            "administrative_area_level_1",
            "political"
          ]
        },
        {
          "long_name": "United States",
          "short_name": "US",
          "types": [
            "country",
            "political"
          ]
        },
        {
          "long_name": "08088",
          "short_name": "08088",
          "types": [
            "postal_code"
          ]
        },
        {
          "long_name": "1133",
          "short_name": "1133",
          "types": [
            "postal_code_suffix"
          ]
        }
      ],
      "formatted_address": "182 Dorchester Dr, Southampton Township, NJ 08088, USA",
      "geometry": {
        "location": {
          "lat": 39.89859999999999,
          "lng": -74.7053
        },
        "location_type": "ROOFTOP",
        "viewport": {
          "northeast": {
            "lat": 39.8999489802915,
            "lng": -74.7039510197085
          },
          "southwest": {
            "lat": 39.8972510197085,
            "lng": -74.7066489802915
          }
        }
      },
      "place_id": "ChIJzTJoWN84wYkR3D0xf1_hVKY",
      "types": [
        "street_address"
      ]
    },
    {
      "address_components": [
        {
          "long_name": "Leisuretowne",
          "short_name": "Leisuretowne",
          "types": [
            "neighborhood",
            "political"
          ]
        },
        {
          "long_name": "Southampton Township",
          "short_name": "Southampton Township",
          "types": [
            "locality",
            "political"
          ]
        },
        {
          "long_name": "Burlington County",
          "short_name": "Burlington County",
          "types": [
            "administrative_area_level_2",
            "political"
          ]
        },
        {
          "long_name": "New Jersey",
          "short_name": "NJ",
          "types": [
            "administrative_area_level_1",
            "political"
          ]
        },
        {
          "long_name": "United States",
          "short_name": "US",
          "types": [
            "country",
            "political"
          ]
        },
        {
          "long_name": "08088",
          "short_name": "08088",
          "types": [
            "postal_code"
          ]
        }
      ],
      "formatted_address": "Leisuretowne, Southampton Township, NJ 08088, USA",
      "geometry": {
        "bounds": {
          "northeast": {
            "lat": 39.918994,
            "lng": -74.68196379999999
          },
          "southwest": {
            "lat": 39.8856671,
            "lng": -74.7207421
          }
        },
        "location": {
          "lat": 39.892337,
          "lng": -74.7021031
        },
        "location_type": "APPROXIMATE",
        "viewport": {
          "northeast": {
            "lat": 39.918994,
            "lng": -74.68196379999999
          },
          "southwest": {
            "lat": 39.8856671,
            "lng": -74.7207421
          }
        }
      },
      "place_id": "ChIJkTpS1d44wYkRxjE5YJi5Ph0",
      "types": [
        "neighborhood",
        "political"
      ]
    },
    {
      "address_components": [
        {
          "long_name": "Southampton Township",
          "short_name": "Southampton Township",
          "types": [
            "locality",
            "political"
          ]
        },
        {
          "long_name": "Burlington County",
          "short_name": "Burlington County",
          "types": [
            "administrative_area_level_2",
            "political"
          ]
        },
        {
          "long_name": "New Jersey",
          "short_name": "NJ",
          "types": [
            "administrative_area_level_1",
            "political"
          ]
        },
        {
          "long_name": "United States",
          "short_name": "US",
          "types": [
            "country",
            "political"
          ]
        }
      ],
      "formatted_address": "Southampton Township, NJ, USA",
      "geometry": {
        "bounds": {
          "northeast": {
            "lat": 39.982245,
            "lng": -74.5965229
          },
          "southwest": {
            "lat": 39.8628819,
            "lng": -74.79128
          }
        },
        "location": {
          "lat": 39.9274288,
          "lng": -74.7265791
        },
        "location_type": "APPROXIMATE",
        "viewport": {
          "northeast": {
            "lat": 39.982245,
            "lng": -74.5965229
          },
          "southwest": {
            "lat": 39.8628819,
            "lng": -74.79128
          }
        }
      },
      "place_id": "ChIJE8KLN14YwYkRli4wQcrP4BU",
      "types": [
        "locality",
        "political"
      ]
    },
    {
      "address_components": [
        {
          "long_name": "08088",
          "short_name": "08088",
          "types": [
            "postal_code"
          ]
        },
        {
          "long_name": "Vincentown",
          "short_name": "Vincentown",
          "types": [
            "neighborhood",
            "political"
          ]
        },
        {
          "long_name": "New Jersey",
          "short_name": "NJ",
          "types": [
            "administrative_area_level_1",
            "political"
          ]
        },
        {
          "long_name": "United States",
          "short_name": "US",
          "types": [
            "country",
            "political"
          ]
        }
      ],
      "formatted_address": "Vincentown, NJ 08088, USA",
      "geometry": {
        "bounds": {
          "northeast": {
            "lat": 39.982245,
            "lng": -74.5028239
          },
          "southwest": {
            "lat": 39.716505,
            "lng": -74.82584
          }
        },
        "location": {
          "lat": 39.8388924,
          "lng": -74.7102958
        },
        "location_type": "APPROXIMATE",
        "viewport": {
          "northeast": {
            "lat": 39.982245,
            "lng": -74.5028239
          },
          "southwest": {
            "lat": 39.716505,
            "lng": -74.82584
          }
        }
      },
      "place_id": "ChIJ1Tc4LP07wYkRdsN8qMbMbOc",
      "postcode_localities": [
        "Shamong",
        "Southampton Township",
        "Tabernacle"
      ],
      "types": [
        "postal_code"
      ]
    },
    {
      "address_components": [
        {
          "long_name": "Burlington County",
          "short_name": "Burlington County",
          "types": [
            "administrative_area_level_2",
            "political"
          ]
        },
        {
          "long_name": "New Jersey",
          "short_name": "NJ",
          "types": [
            "administrative_area_level_1",
            "political"
          ]
        },
        {
          "long_name": "United States",
          "short_name": "US",
          "types": [
            "country",
            "political"
          ]
        }
      ],
      "formatted_address": "Burlington County, NJ, USA",
      "geometry": {
        "bounds": {
          "northeast": {
            "lat": 40.184235,
            "lng": -74.38978999999999
          },
          "southwest": {
            "lat": 39.540837,
            "lng": -75.054844
          }
        },
        "location": {
          "lat": 39.8558488,
          "lng": -74.6868815
        },
        "location_type": "APPROXIMATE",
        "viewport": {
          "northeast": {
            "lat": 40.184235,
            "lng": -74.38978999999999
          },
          "southwest": {
            "lat": 39.540837,
            "lng": -75.054844
          }
        }
      },
      "place_id": "ChIJe3N0AJddwYkRACBgX3eEhqw",
      "types": [
        "administrative_area_level_2",
        "political"
      ]
    },
    {
      "address_components": [
        {
          "long_name": "New Jersey",
          "short_name": "NJ",
          "types": [
            "administrative_area_level_1",
            "political"
          ]
        },
        {
          "long_name": "United States",
          "short_name": "US",
          "types": [
            "country",
            "political"
          ]
        }
      ],
      "formatted_address": "New Jersey, USA",
      "geometry": {
        "bounds": {
          "northeast": {
            "lat": 41.357423,
            "lng": -73.9024391
          },
          "southwest": {
            "lat": 38.9285589,
            "lng": -75.5597921
          }
        },
        "location": {
          "lat": 40.0583238,
          "lng": -74.4056612
        },
        "location_type": "APPROXIMATE",
        "viewport": {
          "northeast": {
            "lat": 41.357423,
            "lng": -73.9024391
          },
          "southwest": {
            "lat": 38.9286032,
            "lng": -75.5597921
          }
        }
      },
      "place_id": "ChIJn0AAnpX7wIkRjW0_-Ad70iw",
      "types": [
        "administrative_area_level_1",
        "political"
      ]
    },
    {
      "address_components": [
        {
          "long_name": "United States",
          "short_name": "US",
          "types": [
            "country",
            "political"
          ]
        }
      ],
      "formatted_address": "United States",
      "geometry": {
        "bounds": {
          "northeast": {
            "lat": 71.3867745,
            "lng": -66.9502861
          },
          "southwest": {
            "lat": 18.9106768,
            "lng": 172.4458955
          }
        },
        "location": {
          "lat": 37.09024,
          "lng": -95.712891
        },
        "location_type": "APPROXIMATE",
        "viewport": {
          "northeast": {
            "lat": 49.38,
            "lng": -66.94
          },
          "southwest": {
            "lat": 25.82,
            "lng": -124.39
          }
        }
      },
      "place_id": "ChIJCzYy5IS16lQRQrfeQ5K5Oxw",
      "types": [
        "country",
        "political"
      ]
    }
  ],
  "status": "OK"
}
