{
  "results": [
    {
      "address_components": [
        {
          "long_name": "27124-27140",
          "short_name": "27124-27140",
          "types": [
            "street_number"
          ]
        },
        {
          "long_name": "Nebraska Street",
          "short_name": "Nebraska St",
          "types": [
            "route"
          ]
        },
        {
          "long_name": "Nickerson",
          "short_name": "Nickerson",
          "types": [
            "locality",
            "political"
          ]
        },
        {
          "long_name": "6",
          "short_name": "6",
          "types": [
            "administrative_area_level_3",
            "political"
          ]
        },
        {
          "long_name": "Washington County",
          "short_name": "Washington County",
          "types": [
            "administrative_area_level_2",
            "political"
          ]
        },
        {
          "long_name": "Nebraska",
          "short_name": "NE",
          "types": [
            "administrative_area_level_1",
            "political"
          ]
        },
        {
          "long_name": "United States",
          "short_name": "US",
          "types": [
            "country",
            "political"
          ]
        },
        {
          "long_name": "68044",
          "short_name": "68044",
          "types": [
            "postal_code"
          ]
        },
        {
          "long_name": "2504",
          "short_name": "2504",
          "types": [
            "postal_code_suffix"
          ]
        }
      ],
      "formatted_address": "27124-27140 Nebraska St, Nickerson, NE 68044, USA",
      "geometry": {
        "bounds": {
          "northeast": {
            "lat": 41.537924,
            "lng": -96.4260566
          },
          "southwest": {
            "lat": 41.5379032,
            "lng": -96.4279693
          }
        },
        "location": {
          "lat": 41.5379203,
          "lng": -96.42718400000001
        },
        "location_type": "RANGE_INTERPOLATED",
        "viewport": {
          "northeast": {
            "lat": 41.5392625802915,
            "lng": -96.4256639697085
          },
          "southwest": {
            "lat": 41.5365646197085,
            "lng": -96.42836193029152
          }
        }
      },
      "place_id": "EjEyNzEyNC0yNzE0MCBOZWJyYXNrYSBTdCwgTmlja2Vyc29uLCBORSA2ODA0NCwgVVNB",
      "types": [
        "street_address"
      ]
    },
    {
      "address_components": [
        {
          "long_name": "68044",
          "short_name": "68044",
          "types": [
            "postal_code"
          ]
        },
        {
          "long_name": "Nickerson",
          "short_name": "Nickerson",
          "types": [
            "locality",
            "political"
          ]
        },
        {
          "long_name": "Nebraska",
          "short_name": "NE",
          "types": [
            "administrative_area_level_1",
            "political"
          ]
        },
        {
          "long_name": "United States",
          "short_name": "US",
          "types": [
            "country",
            "political"
          ]
        }
      ],
      "formatted_address": "Nickerson, NE 68044, USA",
      "geometry": {
        "bounds": {
          "northeast": {
            "lat": 41.5967541,
            "lng": -96.367217
          },
          "southwest": {
            "lat": 41.4760549,
            "lng": -96.5410789
          }
        },
        "location": {
          "lat": 41.5507008,
          "lng": -96.4396888
        },
        "location_type": "APPROXIMATE",
        "viewport": {
          "northeast": {
            "lat": 41.5967541,
            "lng": -96.367217
          },
          "southwest": {
            "lat": 41.4760549,
            "lng": -96.5410789
          }
        }
      },
      "place_id": "ChIJv0a_NfdikYcRNQgJnkJnnUc",
      "postcode_localities": [
        "Fontanelle",
        "Nickerson"
      ],
      "types": [
        "postal_code"
      ]
    },
    {
      "address_components": [
        {
          "long_name": "6",
          "short_name": "6",
          "types": [
            "administrative_area_level_3",
            "political"
          ]
        },
        {
          "long_name": "Washington County",
          "short_name": "Washington County",
          "types": [
            "administrative_area_level_2",
            "political"
          ]
        },
        {
          "long_name": "Nebraska",
          "short_name": "NE",
          "types": [
            "administrative_area_level_1",
            "political"
          ]
        },
        {
          "long_name": "United States",
          "short_name": "US",
          "types": [
            "country",
            "political"
          ]
        }
      ],
      "formatted_address": "6, NE, USA",
      "geometry": {
        "bounds": {
          "northeast": {
            "lat": 41.6109859,
            "lng": -96.1476989
          },
          "southwest": {
            "lat": 41.479673,
            "lng": -96.444356
          }
        },
        "location": {
          "lat": 41.5495797,
          "lng": -96.2800864
        },
        "location_type": "APPROXIMATE",
        "viewport": {
          "northeast": {
            "lat": 41.6109859,
            "lng": -96.1476989
          },
          "southwest": {
            "lat": 41.479673,
            "lng": -96.444356
          }
        }
      },
      "place_id": "ChIJO5rXdbTbk4cRT7-gzsV7lFA",
      "types": [
        "administrative_area_level_3",
        "political"
      ]
    },
    {
      "address_components": [
        {
          "long_name": "Washington County",
          "short_name": "Washington County",
          "types": [
            "administrative_area_level_2",
            "political"
          ]
        },
        {
          "long_name": "Nebraska",
          "short_name": "NE",
          "types": [
            "administrative_area_level_1",
            "political"
          ]
        },
        {
          "long_name": "United States",
          "short_name": "US",
          "types": [
            "country",
            "political"
          ]
        }
      ],
      "formatted_address": "Washington County, NE, USA",
      "geometry": {
        "bounds": {
          "northeast": {
            "lat": 41.6836589,
            "lng": -95.9195369
          },
          "southwest": {
            "lat": 41.390752,
            "lng": -96.444795
          }
        },
        "location": {
          "lat": 41.5541889,
          "lng": -96.19513200000002
        },
        "location_type": "APPROXIMATE",
        "viewport": {
          "northeast": {
            "lat": 41.6836589,
            "lng": -95.9195369
          },
          "southwest": {
            "lat": 41.390752,
            "lng": -96.444795
          }
        }
      },
      "place_id": "ChIJbQYEfuHEk4cR5Ic2VlDx24E",
      "types": [
        "administrative_area_level_2",
        "political"
      ]
    },
    {
      "address_components": [
        {
          "long_name": "Nebraska",
          "short_name": "NE",
          "types": [
            "administrative_area_level_1",
            "political"
          ]
        },
        {
          "long_name": "United States",
          "short_name": "US",
          "types": [
            "country",
            "political"
          ]
        }
      ],
      "formatted_address": "Nebraska, USA",
      "geometry": {
        "bounds": {
          "northeast": {
            "lat": 43.00170689999999,
            "lng": -95.30829000000001
          },
          "southwest": {
            "lat": 39.999932,
            "lng": -104.053514
          }
        },
        "location": {
          "lat": 41.4925374,
          "lng": -99.9018131
        },
        "location_type": "APPROXIMATE",
        "viewport": {
          "northeast": {
            "lat": 43.00170689999999,
            "lng": -95.30829000000001
          },
          "southwest": {
            "lat": 39.999932,
            "lng": -104.053514
          }
        }
      },
      "place_id": "ChIJ7fwMtciNk4cRxArzDwyQJ6E",
      "types": [
        "administrative_area_level_1",
        "political"
      ]
    },
    {
      "address_components": [
        {
          "long_name": "United States",
          "short_name": "US",
          "types": [
            "country",
            "political"
          ]
        }
      ],
      "formatted_address": "United States",
      "geometry": {
        "bounds": {
          "northeast": {
            "lat": 71.3867745,
            "lng": -66.9502861
          },
          "southwest": {
            "lat": 18.9106768,
            "lng": 172.4458955
          }
        },
        "location": {
          "lat": 37.09024,
          "lng": -95.712891
        },
        "location_type": "APPROXIMATE",
        "viewport": {
          "northeast": {
            "lat": 49.38,
            "lng": -66.94
          },
          "southwest": {
            "lat": 25.82,
            "lng": -124.39
          }
        }
      },
      "place_id": "ChIJCzYy5IS16lQRQrfeQ5K5Oxw",
      "types": [
        "country",
        "political"
      ]
    }
  ],
  "status": "OK"
}
