{
  "results": [
    {
      "address_components": [
        {
          "long_name": "214",
          "short_name": "214",
          "types": [
            "street_number"
          ]
        },
        {
          "long_name": "East Front Street",
          "short_name": "E Front St",
          "types": [
            "route"
          ]
        },
        {
          "long_name": "Syracuse",
          "short_name": "Syracuse",
          "types": [
            "locality",
            "political"
          ]
        },
        {
          "long_name": "Mill Creek Township",
          "short_name": "Mill Creek Township",
          "types": [
            "administrative_area_level_3",
            "political"
          ]
        },
        {
          "long_name": "Morgan County",
          "short_name": "Morgan County",
          "types": [
            "administrative_area_level_2",
            "political"
          ]
        },
        {
          "long_name": "Missouri",
          "short_name": "MO",
          "types": [
            "administrative_area_level_1",
            "political"
          ]
        },
        {
          "long_name": "United States",
          "short_name": "US",
          "types": [
            "country",
            "political"
          ]
        },
        {
          "long_name": "65354",
          "short_name": "65354",
          "types": [
            "postal_code"
          ]
        },
        {
          "long_name": "1043",
          "short_name": "1043",
          "types": [
            "postal_code_suffix"
          ]
        }
      ],
      "formatted_address": "214 E Front St, Syracuse, MO 65354, USA",
      "geometry": {
        "location": {
          "lat": 38.6696294,
          "lng": -92.8739653
        },
        "location_type": "ROOFTOP",
        "viewport": {
          "northeast": {
            "lat": 38.6709783802915,
            "lng": -92.87261631970848
          },
          "southwest": {
            "lat": 38.6682804197085,
            "lng": -92.8753142802915
          }
        }
      },
      "place_id": "ChIJE40SmMhjw4cRWlIxPV7v5gM",
      "types": [
        "street_address"
      ]
    },
    {
      "address_components": [
        {
          "long_name": "Syracuse",
          "short_name": "Syracuse",
          "types": [
            "locality",
            "political"
          ]
        },
        {
          "long_name": "Mill Creek Township",
          "short_name": "Mill Creek Township",
          "types": [
            "administrative_area_level_3",
            "political"
          ]
        },
        {
          "long_name": "Morgan County",
          "short_name": "Morgan County",
          "types": [
            "administrative_area_level_2",
            "political"
          ]
        },
        {
          "long_name": "Missouri",
          "short_name": "MO",
          "types": [
            "administrative_area_level_1",
            "political"
          ]
        },
        {
          "long_name": "United States",
          "short_name": "US",
          "types": [
            "country",
            "political"
          ]
        },
        {
          "long_name": "65354",
          "short_name": "65354",
          "types": [
            "postal_code"
          ]
        }
      ],
      "formatted_address": "Syracuse, MO 65354, USA",
      "geometry": {
        "bounds": {
          "northeast": {
            "lat": 38.6734949,
            "lng": -92.8693869
          },
          "southwest": {
            "lat": 38.665703,
            "lng": -92.8834229
          }
        },
        "location": {
          "lat": 38.6700209,
          "lng": -92.8732509
        },
        "location_type": "APPROXIMATE",
        "viewport": {
          "northeast": {
            "lat": 38.6734949,
            "lng": -92.8693869
          },
          "southwest": {
            "lat": 38.665703,
            "lng": -92.8834229
          }
        }
      },
      "place_id": "ChIJBxviZchjw4cRMZoGKs8_IEQ",
      "types": [
        "locality",
        "political"
      ]
    },
    {
      "address_components": [
        {
          "long_name": "65354",
          "short_name": "65354",
          "types": [
            "postal_code"
          ]
        },
        {
          "long_name": "Syracuse",
          "short_name": "Syracuse",
          "types": [
            "locality",
            "political"
          ]
        },
        {
          "long_name": "Missouri",
          "short_name": "MO",
          "types": [
            "administrative_area_level_1",
            "political"
          ]
        },
        {
          "long_name": "United States",
          "short_name": "US",
          "types": [
            "country",
            "political"
          ]
        }
      ],
      "formatted_address": "Syracuse, MO 65354, USA",
      "geometry": {
        "bounds": {
          "northeast": {
            "lat": 38.699204,
            "lng": -92.83417209999999
          },
          "southwest": {
            "lat": 38.57711,
            "lng": -92.9508778
          }
        },
        "location": {
          "lat": 38.6489216,
          "lng": -92.88764359999999
        },
        "location_type": "APPROXIMATE",
        "viewport": {
          "northeast": {
            "lat": 38.699204,
            "lng": -92.83417209999999
          },
          "southwest": {
            "lat": 38.57711,
            "lng": -92.9508778
          }
        }
      },
      "place_id": "ChIJBWIDbxRjw4cRyuExNOhksWQ",
      "types": [
        "postal_code"
      ]
    },
    {
      "address_components": [
        {
          "long_name": "Mill Creek Township",
          "short_name": "Mill Creek Township",
          "types": [
            "administrative_area_level_3",
            "political"
          ]
        },
        {
          "long_name": "Morgan County",
          "short_name": "Morgan County",
          "types": [
            "administrative_area_level_2",
            "political"
          ]
        },
        {
          "long_name": "Missouri",
          "short_name": "MO",
          "types": [
            "administrative_area_level_1",
            "political"
          ]
        },
        {
          "long_name": "United States",
          "short_name": "US",
          "types": [
            "country",
            "political"
          ]
        }
      ],
      "formatted_address": "Mill Creek Township, MO, USA",
      "geometry": {
        "bounds": {
          "northeast": {
            "lat": 38.6855149,
            "lng": -92.7859869
          },
          "southwest": {
            "lat": 38.500023,
            "lng": -92.9374079
          }
        },
        "location": {
          "lat": 38.5967552,
          "lng": -92.8776638
        },
        "location_type": "APPROXIMATE",
        "viewport": {
          "northeast": {
            "lat": 38.6855149,
            "lng": -92.7859869
          },
          "southwest": {
            "lat": 38.500023,
            "lng": -92.9374079
          }
        }
      },
      "place_id": "ChIJa7ttud6dxIcRrET2dLiDz2E",
      "types": [
        "administrative_area_level_3",
        "political"
      ]
    },
    {
      "address_components": [
        {
          "long_name": "Morgan County",
          "short_name": "Morgan County",
          "types": [
            "administrative_area_level_2",
            "political"
          ]
        },
        {
          "long_name": "Missouri",
          "short_name": "MO",
          "types": [
            "administrative_area_level_1",
            "political"
          ]
        },
        {
          "long_name": "United States",
          "short_name": "US",
          "types": [
            "country",
            "political"
          ]
        }
      ],
      "formatted_address": "Morgan County, MO, USA",
      "geometry": {
        "bounds": {
          "northeast": {
            "lat": 38.69307,
            "lng": -92.62518879999999
          },
          "southwest": {
            "lat": 38.1896499,
            "lng": -93.0774219
          }
        },
        "location": {
          "lat": 38.3661344,
          "lng": -92.8577105
        },
        "location_type": "APPROXIMATE",
        "viewport": {
          "northeast": {
            "lat": 38.69307,
            "lng": -92.62518879999999
          },
          "southwest": {
            "lat": 38.1896499,
            "lng": -93.0774219
          }
        }
      },
      "place_id": "ChIJhaNIffSXxIcR6vlPGkDRS18",
      "types": [
        "administrative_area_level_2",
        "political"
      ]
    },
    {
      "address_components": [
        {
          "long_name": "Missouri",
          "short_name": "MO",
          "types": [
            "administrative_area_level_1",
            "political"
          ]
        },
        {
          "long_name": "United States",
          "short_name": "US",
          "types": [
            "country",
            "political"
          ]
        }
      ],
      "formatted_address": "Missouri, USA",
      "geometry": {
        "bounds": {
          "northeast": {
            "lat": 40.61364,
            "lng": -89.09949399999999
          },
          "southwest": {
            "lat": 35.9956829,
            "lng": -95.774704
          }
        },
        "location": {
          "lat": 37.9642529,
          "lng": -91.8318334
        },
        "location_type": "APPROXIMATE",
        "viewport": {
          "northeast": {
            "lat": 40.61364,
            "lng": -89.09949399999999
          },
          "southwest": {
            "lat": 35.9956829,
            "lng": -95.774704
          }
        }
      },
      "place_id": "ChIJfeMiSNXmwIcRcr1mBFnEW7U",
      "types": [
        "administrative_area_level_1",
        "political"
      ]
    },
    {
      "address_components": [
        {
          "long_name": "United States",
          "short_name": "US",
          "types": [
            "country",
            "political"
          ]
        }
      ],
      "formatted_address": "United States",
      "geometry": {
        "bounds": {
          "northeast": {
            "lat": 71.3867745,
            "lng": -66.9502861
          },
          "southwest": {
            "lat": 18.9106768,
            "lng": 172.4458955
          }
        },
        "location": {
          "lat": 37.09024,
          "lng": -95.712891
        },
        "location_type": "APPROXIMATE",
        "viewport": {
          "northeast": {
            "lat": 49.38,
            "lng": -66.94
          },
          "southwest": {
            "lat": 25.82,
            "lng": -124.39
          }
        }
      },
      "place_id": "ChIJCzYy5IS16lQRQrfeQ5K5Oxw",
      "types": [
        "country",
        "political"
      ]
    }
  ],
  "status": "OK"
}
